{"@context": "http://schema.org", "@type": "Movie", "url": "/title/tt4547056/", "name": "The Girl with All the Gifts", "image": "https://m.media-amazon.com/images/M/MV5BMjQ0NzA4NDcxM15BMl5BanBnXkFtZTgwMTk1NjUzOTE@._V1_.jpg", "genre": ["Action", "Adventure", "Drama", "Horror", "Sci-Fi", "Thriller"], "contentRating": "R", "actor": [{"@type": "Person", "url": "/name/nm6451469/", "name": "Sennia Nanua"}, {"@type": "Person", "url": "/name/nm6160535/", "name": "Fisayo Akinade"}, {"@type": "Person", "url": "/name/nm4625680/", "name": "Dominique Tipper"}, {"@type": "Person", "url": "/name/nm0175916/", "name": "Paddy Considine"}], "director": [{"@type": "Person", "url": "/name/nm1142073/", "name": "Colm McCarthy"}], "creator": [{"@type": "Person", "url": "/name/nm1259998/", "name": "Mike Carey"}, {"@type": "Person", "url": "/name/nm1259998/", "name": "Mike Carey"}, {"@type": "Organization", "url": "/company/co0375874/"}, {"@type": "Organization", "url": "/company/co0381819/"}, {"@type": "Organization", "url": "/company/co0398856/"}, {"@type": "Organization", "url": "/company/co0529888/"}], "description": "The Girl with All the Gifts is a movie starring Sennia Nanua, Fisayo Akinade, and Dominique Tipper. A scientist and a teacher living in a dystopian future embark on a journey of survival with a special young girl named Melanie.", "datePublished": "2016-09-23", "keywords": "experiment,bitten by a zombie,feral child,scientist,cure", "aggregateRating": [{"@type": "AggregateRating", "ratingCount": 52635, "bestRating": "10.0", "worstRating": "1.0", "ratingValue": "6.6"}], "duration": "PT1H51M", "trailer": [{"@type": "VideoObject", "name": "U.S. Trailer", "embedUrl": "/video/imdb/vi3426661913", "thumbnail": {"@type": "ImageObject", "contentUrl": "https://m.media-amazon.com/images/M/MV5BMTY1OTc5NDYwNV5BMl5BanBnXkFtZTgwMjk2NTMwMTI@._V1_.jpg"}, "thumbnailUrl": "https://m.media-amazon.com/images/M/MV5BMTY1OTc5NDYwNV5BMl5BanBnXkFtZTgwMjk2NTMwMTI@._V1_.jpg", "description": "A scientist and a teacher living in a dystopian future embark on a journey of survival with a special young girl named Melanie.", "uploadDate": "2017-01-06T04:33:22Z"}], "EntryURL": "https://www.imdb.com/title/tt4547056", "EntryPath": "Favorites/Movies/snapshot/The-Girl-with-All-the-Gifts", "Entry_py": "Favorites/Movies/snapshot/The-Girl-with-All-the-Gifts/info.py", "Entry_json": "Favorites/Movies/snapshot/The-Girl-with-All-the-Gifts/entry.json", "Entry_thumb": "Favorites/Movies/snapshot/The-Girl-with-All-the-Gifts/thumb.jpg", "EntryAdded": "2017-05-30"}