{"Actors": ["Brian Lawler"], "Added": "2013-08-18", "Countries": [], "Description": "\nTerms and Conditions May Apply: A documentary that exposes what corporations and governments learn about people through Internet and cell phone usage, and what can be done about it ... if anything.\n", "Director": ["Cullen Hoback"], "Genres": ["Documentary"], "IMDB": "http://www.imdb.com/title/tt2084953", "PrimeWire": "http://www.primewire.ag/watch-2741123-Terms-and-Conditions-May-Apply", "Ratings": {"IMDB": "7.4/10", "Metascore": "68%", "PrimeWire": "4.28/5", "RT": "86%", "Votes": "229"}, "Released": "2013-07-12", "Runtime": "79 mins ", "ThumbURL": "http://images.primewire.ag/thumbs/2741123_Terms_and_Conditions_May_Apply.jpg", "Title": "Terms-and-Conditions-May-Apply", "EntryPath": "W:\\Portfolio\\PersonalWebsite\\Favorites/Movies/snapshot//Terms-and-Conditions-May-Apply", "EntryURL": "https://www.imdb.com/title/tt2084953", "Entry_py": "W:\\Portfolio\\PersonalWebsite\\Favorites/Movies/snapshot//Terms-and-Conditions-May-Apply/info.py", "Entry_php": "W:\\Portfolio\\PersonalWebsite\\Favorites/Movies/snapshot//Terms-and-Conditions-May-Apply/info.php", "Entry_json": "W:\\Portfolio\\PersonalWebsite\\Favorites/Movies/snapshot//Terms-and-Conditions-May-Apply/entry.json"}